jupyter_server_client/__init__.py
jupyter_server_client/_version.py
jupyter_server_client/client.py
jupyter_server_client/exceptions.py
jupyter_server_client/http_client.py
jupyter_server_client/models.py
jupyter_server_client/managers/__init__.py
jupyter_server_client/managers/contents.py
jupyter_server_client/managers/kernels.py
jupyter_server_client/managers/kernelspecs.py
jupyter_server_client/managers/sessions.py
jupyter_server_client/managers/terminals.py
jupyter_server_client-0.1.1.dist-info/METADATA
jupyter_server_client-0.1.1.dist-info/WHEEL
jupyter_server_client-0.1.1.dist-info/licenses/LICENSE
jupyter_server_client-0.1.1.dist-info/RECORD
