Metadata-Version: 2.4
Name: jupyter-server-client
Version: 0.1.1
Summary: A client library for interacting with Jupyter servers - focused on server management and kernel listing
Project-URL: Homepage, https://github.com/datalayer/jupyter-server-client
Project-URL: Documentation, https://github.com/datalayer/jupyter-server-client#readme
Project-URL: Repository, https://github.com/datalayer/jupyter-server-client.git
Project-URL: Issues, https://github.com/datalayer/jupyter-server-client/issues
Author-email: Datalayer <info@datalayer.io>
License: BSD 3-Clause License
License-File: LICENSE
Keywords: client,datalayer,jupyter,kernels,server
Classifier: Framework :: Jupyter
Classifier: Framework :: Jupyter :: JupyterLab
Classifier: Framework :: Jupyter :: JupyterLab :: 4
Classifier: Intended Audience :: Developers
Classifier: Intended Audience :: Science/Research
Classifier: Intended Audience :: System Administrators
Classifier: License :: OSI Approved :: BSD License
Classifier: Programming Language :: Python
Classifier: Programming Language :: Python :: 3.8
Classifier: Programming Language :: Python :: 3.9
Classifier: Programming Language :: Python :: 3.10
Classifier: Programming Language :: Python :: 3.11
Classifier: Programming Language :: Python :: 3.12
Requires-Python: >=3.8
Requires-Dist: pydantic>=2.0.0
Requires-Dist: requests>=2.25.0
Requires-Dist: typing-extensions>=4.0.0; python_version < '3.10'
Provides-Extra: full
Requires-Dist: jupyter-kernel-client>=0.6.0; extra == 'full'
Requires-Dist: jupyter-nbmodel-client>=0.11.0; extra == 'full'
Provides-Extra: kernel
Requires-Dist: jupyter-kernel-client>=0.6.0; extra == 'kernel'
Provides-Extra: lint
Requires-Dist: pre-commit>=3.0.0; extra == 'lint'
Provides-Extra: nbmodel
Requires-Dist: jupyter-nbmodel-client>=0.11.0; extra == 'nbmodel'
Provides-Extra: test
Requires-Dist: httpx>=0.24.0; extra == 'test'
Requires-Dist: jupyter-kernel-client>=0.6.0; extra == 'test'
Requires-Dist: jupyter-nbmodel-client>=0.11.0; extra == 'test'
Requires-Dist: pytest-asyncio>=0.21.0; extra == 'test'
Requires-Dist: pytest>=6.0; extra == 'test'
Requires-Dist: respx>=0.20.0; extra == 'test'
Provides-Extra: typing
Requires-Dist: mypy>=1.0.0; extra == 'typing'
